[
  {
    "name": "Prednisone",
    "price": 550.72,
    "_seller": "Gary Stevens"
  },
  {
    "name": "DAYWEAR PLUS MULTI PROTECTION TINTED MOISTURIZER",
    "price": 555.12,
    "_seller": "Betty Lawson"
  },
  {
    "name": "Topiramate",
    "price": 578.77,
    "_seller": "Betty Lawson"
  },
  {
    "name": "No7 Protect and Perfect Foundation Sunscreen Broad Spectrum SPF 15 Cool Ivory",
    "price": 616.19,
    "_seller": "null Mitchell"
  },
  {
    "name": "ziprasidone hydrochloride",
    "price": 628.66,
    "_seller": "Anna Clark"
  },
  {
    "name": "Amitiza",
    "price": 666.58,
    "_seller": "Gary Stevens"
  },
  {
    "name": "Acnezzol Base",
    "price": 710.60,
    "_seller": "Fred Allen"
  },
  {
    "name": "Warfarin Sodium",
    "price": 770.05,
    "_seller": "Carl Lawson"
  },
  {
    "name": "Isosorbide Mononitrate",
    "price": 789.91,
    "_seller": "Eugene Stewart"
  },
  {
    "name": "LV-FX",
    "price": 820.87,
    "_seller": "null Mitchell"
  },
  {
    "name": "IOPE SUPER VITAL",
    "price": 824.68,
    "_seller": "Eugene Stewart"
  },
  {
    "name": "Perrigo Benzoyl Peroxide",
    "price": 873.24,
    "_seller": "null Mitchell"
  },
  {
    "name": "Aspirin",
    "price": 925.45,
    "_seller": "Anna Clark"
  },
  {
    "name": "Glipizide and Metformin Hydrochloride",
    "price": 953.60,
    "_seller": "Clarence Fowler"
  },
  {
    "name": "Metformin Hydrochloride",
    "price": 953.99,
    "_seller": "Carl Daniels"
  },
  {
    "name": "Dawn Ultra Antibacterial Hand",
    "price": 969.86,
    "_seller": "Clarence Fowler"
  },
  {
    "name": "Retin-A MICRO",
    "price": 995.98,
    "_seller": "Anna Clark"
  }
]
